{
  "dockerFile": "node.Dockerfile",
  "extensions": [
    "ms-vsonline.vsonline",
    "GitHub.vscode-pull-request-github",
    "ms-vsliveshare.vsliveshare",
    "visualstudioexptteam.vscodeintellicode",
    "alexdima.copy-relative-path",
    "atlassian.atlascode",
    "codezombiech.gitignore",
    "dbaeumer.vscode-eslint",
    "eamodio.gitlens",
    "editorconfig.editorconfig",
    "esbenp.prettier-vscode",
    "formulahendry.code-runner",
    "gioboa.jira-plugin",
    "gruntfuggly.todo-tree",
    "henriiik.docker-linter",
    "ibm.output-colorizer",
    "inu1255.easy-snippet",
    "johnpapa.vscode-peacock",
    "jasonlhy.hungry-delete",
    "jkjustjoshing.vscode-text-pastry",
    "mhutchie.git-graph",
    "mikestead.dotenv",
    "moshfeu.compare-folders-insider",
    "moshfeu.diff-merge",
    "ms-azuretools.vscode-docker",
    "ms-vscode.azure-account",
    "ms-vscode.js-debug",
    "ms-vscode.js-debug-companion",
    "ms-vscode.node-debug",
    "ms-vscode.node-debug2",
    "ms-vscode.references-view",
    "ms-vscode.vscode-js-profile-table",
    "nhoizey.gremlins",
    "pkief.material-icon-theme",
    "pnp.polacode",
    "richie5um2.vscode-sort-json",
    "steoates.autoimport",
    "stkb.rewrap",
    "streetsidesoftware.code-spell-checker",
    "stylelint.vscode-stylelint",
    "svipas.control-snippets",
    "tomoki1207.pdf",
    "tyriar.sort-lines",
    "visualstudioexptteam.vscodeintellicode",
    "vsls-contrib.codetour",
    "vsls-contrib.gistfs",
    "zhuangtongfa.material-theme"
  ],
  "forwardPorts": [3000],
  "name": "AB: Containerized Development - Node",
  "postCreateCommand": "yarn install",
  "remoteUser": "node",
  "settings": {
    "[json]": {
      "editor.defaultFormatter": "esbenp.prettier-vscode"
    },
    "[jsonc]": {
      "editor.defaultFormatter": "esbenp.prettier-vscode"
    },
    "atlascode.bitbucket.enabled": false,
    "atlascode.jira.enabled": true,
    "atlascode.jira.explorer.assignedIssueJql": "assignee=currentUser() and resolution = Unresolved",
    "atlascode.jira.explorer.enabled": true,
    "atlascode.jira.explorer.nestSubtasks": true,
    "atlascode.jira.jqlList": [
      {
        "enabled": true,
        "id": "110bea68-bd07-43aa-b1bc-2512556cd473",
        "monitor": true,
        "name": "TPS - My Issues",
        "query": "project in (\"PUZSOC\",\"GAMES\") AND status != resolved and assignee = currentUser() ORDER by rank ASC, priority DESC, updatedDate DESC",
        "siteId": "6002c11a-0ab3-4e92-b2d1-eb97960ab7a6"
      },
      {
        "enabled": true,
        "id": "02142ed5-c4d7-41af-a082-7e16cb33dada",
        "monitor": true,
        "name": "Games/Embed - Issues",
        "query": "project in (Games, EMBEDSERV) AND status != resolved and assignee = currentUser() ORDER by rank ASC, priority DESC, updatedDate DESC",
        "siteId": "6002c11a-0ab3-4e92-b2d1-eb97960ab7a6"
      },
      {
        "enabled": true,
        "id": "486d46cd-29a5-47e7-b5cb-7bdf9625be72",
        "monitor": true,
        "name": "My amuniversal Issues",
        "query": "assignee = currentUser() and status != resolved ORDER BY rank ASC, priority DESC",
        "siteId": "6002c11a-0ab3-4e92-b2d1-eb97960ab7a6"
      },
      {
        "enabled": true,
        "id": "c33593e5-febe-4787-adce-44be66d943ab",
        "monitor": true,
        "name": "My Most Recently Created Issues",
        "query": "reporter = currentUser() AND status != Done ORDER BY updatedDate",
        "siteId": "6002c11a-0ab3-4e92-b2d1-eb97960ab7a6"
      }
    ],
    "atlascode.jira.startWorkBranchTemplate.customPrefixes": [
      "maintenance",
      "story",
      "bug",
      "hotfix",
      "release",
      "research"
    ],
    "atlascode.jira.startWorkBranchTemplate.customTemplate": "{{{prefix}}}/{{{issueKey}}}/{{{summary}}}",
    "atlascode.jira.statusbar.showProject": true,
    "atlascode.jira.statusbar.showUser": false,
    "atlascode.jira.todoIssues.triggers": [
      "TODO:",
      "BUG:",
      "FIXME:",
      "ISSUE:",
      "TODO -"
    ],
    "atlascode.jira.workingSite": {
      "avatarUrl": "https://site-admin-avatar-cdn.prod.public.atl-paas.net/avatars/240/koala.png",
      "baseUrlSuffix": "atlassian.net",
      "id": "6002c11a-0ab3-4e92-b2d1-eb97960ab7a6",
      "name": "amuniversal",
      "scopes": [
        "manage:jira-project",
        "write:jira-work",
        "read:jira-work",
        "read:jira-user"
      ]
    },
    "atlascode.outputLevel": "errors",
    "breadcrumbs.enabled": true,
    "cSpell.enableFiletypes": ["erb", "javascript"],
    "cSpell.enabledLanguageIds": [
      "asciidoc",
      "c",
      "cpp",
      "csharp",
      "css",
      "git-commit",
      "go",
      "handlebars",
      "html",
      "jade",
      "java",
      "javascriptreact",
      "json",
      "jsonc",
      "latex",
      "less",
      "markdown",
      "php",
      "plaintext",
      "pug",
      "python",
      "restructuredtext",
      "rust",
      "scala",
      "scss",
      "text",
      "typescript",
      "typescriptreact",
      "yaml",
      "yml"
    ],
    "cSpell.ignorePaths": [
      "**/package-lock.json",
      "**/node_modules/**",
      "**/vscode-extension/**",
      "**/.git/objects/**",
      ".vscode",
      "coverage/**"
    ],
    "cSpell.language": "en,en-GB",
    "cSpell.userWords": [
      "AUTOML",
      "Adserver",
      "Browserstack",
      "CCPA",
      "Coenraad",
      "Colorstr",
      "Comixology",
      "Confiant",
      "Csrf",
      "DISQUS",
      "Farside",
      "Imgur",
      "Interactables",
      "Leaderboards",
      "Macromedia",
      "Macromedia's",
      "Matic",
      "Meel",
      "Pageview",
      "Parens",
      "Prebid",
      "Preconnect",
      "Puzzazz",
      "Puzzlewright",
      "Qjvz",
      "Shortz's",
      "Shortzian",
      "Sovrn",
      "Steinberg",
      "Styleguide",
      "Teads",
      "Tensorflow",
      "Triplelift",
      "Vqwwq",
      "Waldron",
      "Webistrano",
      "abarrows",
      "adsystem",
      "ajaxloader",
      "amuniversal",
      "amzn",
      "andrewbarrows",
      "animationend",
      "animatronic",
      "appnexus",
      "apstag",
      "authenticatable",
      "autoformat",
      "autotrack",
      "beerslider",
      "bitbucket",
      "browser",
      "browserslist",
      "browserslistrc",
      "bstack",
      "callout",
      "capabilities",
      "captcha",
      "commentable",
      "compat",
      "comscore",
      "content",
      "cookieconsent",
      "cropperjs",
      "crossorigin",
      "crucigramas",
      "cyclomatic",
      "database",
      "datepicker",
      "dependencies",
      "destructable",
      "dev",
      "dilbertcomics",
      "downcase",
      "dximagetransform",
      "erblint",
      "farworks",
      "fasterer",
      "favicons",
      "gamedata",
      "gemfile",
      "gocomics",
      "gocontent",
      "googletag",
      "gsub",
      "gsutil",
      "hfmysql",
      "hfstagedb",
      "hsforms",
      "hspa",
      "hubspot",
      "iefix",
      "iframe",
      "interactable",
      "javascripts",
      "jforce",
      "junit",
      "leaderboard",
      "linkedin",
      "mixins",
      "multisize",
      "museo",
      "noscript",
      "nvmrc",
      "opentype",
      "openx",
      "otterloop",
      "pbjs",
      "polyfill",
      "postload",
      "precompilation",
      "precompile",
      "prefetch",
      "preload",
      "prepend",
      "progid",
      "pubads",
      "pubmatic",
      "puzzlesociety",
      "raty",
      "recaptcha",
      "reenable",
      "rellax",
      "repo",
      "rootonym",
      "roxot",
      "rspec",
      "rubocop",
      "scottadamssays",
      "sharethrough",
      "shortname",
      "smoothscroll",
      "solargraph",
      "sourcepoint",
      "stickybits",
      "strnativekey",
      "stylelint",
      "stylesheet",
      "stylesheets",
      "svgs",
      "swiper",
      "tagid",
      "tbody",
      "tflite",
      "thead",
      "thefarside",
      "truetype",
      "tynt",
      "ubadge",
      "uclick",
      "uexpress",
      "validatable",
      "venatus",
      "webfont",
      "webpacker",
      "woff",
      "workhorse",
      "yamllint"
    ],
    "codespaces.accountProvider": "GitHub",
    "codespaces.defaultExtensions": [
      "ms-vsonline.vsonline",
      "GitHub.vscode-pull-request-github",
      "ms-vsliveshare.vsliveshare",
      "visualstudioexptteam.vscodeintellicode",
      "alexdima.copy-relative-path",
      "atlassian.atlascode",
      "codezombiech.gitignore",
      "dbaeumer.vscode-eslint",
      "eamodio.gitlens",
      "editorconfig.editorconfig",
      "esbenp.prettier-vscode",
      "formulahendry.code-runner",
      "gioboa.jira-plugin",
      "gruntfuggly.todo-tree",
      "henriiik.docker-linter",
      "ibm.output-colorizer",
      "inu1255.easy-snippet",
      "johnpapa.vscode-peacock",
      "jasonlhy.hungry-delete",
      "jkjustjoshing.vscode-text-pastry",
      "mhutchie.git-graph",
      "mikestead.dotenv",
      "moshfeu.compare-folders-insider",
      "moshfeu.diff-merge",
      "ms-azuretools.vscode-docker",
      "ms-vscode.azure-account",
      "ms-vscode.js-debug",
      "ms-vscode.js-debug-companion",
      "ms-vscode.node-debug",
      "ms-vscode.node-debug2",
      "ms-vscode.references-view",
      "ms-vscode.vscode-js-profile-table",
      "nhoizey.gremlins",
      "pkief.material-icon-theme",
      "pnp.polacode",
      "richie5um2.vscode-sort-json",
      "steoates.autoimport",
      "stkb.rewrap",
      "streetsidesoftware.code-spell-checker",
      "stylelint.vscode-stylelint",
      "svipas.control-snippets",
      "tomoki1207.pdf",
      "tyriar.sort-lines",
      "visualstudioexptteam.vscodeintellicode",
      "vsls-contrib.codetour",
      "vsls-contrib.gistfs",
      "zhuangtongfa.material-theme"
    ],
    "codespaces.enableSubmoduleCloning": true,
    "codespaces.featureSet": "insiders",
    "compareFolders.useDiffMerge": true,
    "css.validate": false,
    "debug.console.fontSize": 16,
    "diffEditor.codeLens": true,
    "diffEditor.ignoreTrimWhitespace": true,
    "diffEditor.renderSideBySide": true,
    "editor.accessibilitySupport": "off",
    "editor.codeActionsOnSave": {
      "source.fixAll.eslint": true,
      "source.fixAll.stylelint": true,
      "source.fixAll.tslint": true,
      "source.format.stylelint": true,
      "source.sortJSON.sortJSON": true
    },
    "editor.cursorBlinking": "smooth",
    "editor.cursorSmoothCaretAnimation": true,
    "editor.cursorStyle": "line",
    "editor.emptySelectionClipboard": false,
    "editor.fastScrollSensitivity": 10,
    "editor.find.autoFindInSelection": "never",
    "editor.fontFamily": "Fira Code",
    "editor.fontLigatures": true,
    "editor.fontSize": 16,
    "editor.formatOnPaste": true,
    "editor.formatOnSave": true,
    "editor.hover.delay": 200,
    "editor.minimap.enabled": false,
    "editor.renderControlCharacters": false,
    "editor.renderIndentGuides": true,
    "editor.scrollBeyondLastLine": true,
    "editor.tabCompletion": "onlySnippets",
    "editor.tabSize": 2,
    "editor.wordWrap": "bounded",
    "emmet.includeLanguages": {
      "*.erb": ".html"
    },
    "eslint.alwaysShowStatus": true,
    "eslint.format.enable": true,
    "eslint.lintTask.enable": true,
    "eslint.packageManager": "yarn",
    "explorer.confirmDelete": false,
    "explorer.confirmDragAndDrop": false,
    "extensions.closeExtensionDetailsOnViewChange": true,
    "extensions.ignoreRecommendations": true,
    "extensions.showRecommendationsOnlyOnDemand": true,
    "files.associations": {
      "*.html.erb": "erb",
      "*.js.erb": "js"
    },
    "files.autoSave": "onWindowChange",
    "files.exclude": {
      "**/.history": true,
      "**/.idea": true,
      "**/.vscode": true
    },
    "files.insertFinalNewline": true,
    "files.trimTrailingWhitespace": true,
    "gistpad.playgrounds.showConsole": true,
    "gistpad.playgrounds.stylesheetLanguage": "scss",
    "git.autofetch": true,
    "git.confirmSync": false,
    "git.enableSmartCommit": true,
    "git.inputValidationLength": 200,
    "git.inputValidationSubjectLength": null,
    "git.showPushSuccessNotification": true,
    "github.customPullRequestTitle": true,
    "github.preferedMergeMethod": "merge",
    "githubPullRequests.defaultMergeMethod": "merge",
    "githubPullRequests.showInSCM": true,
    "gitlens.advanced.messages": {
      "suppressFileNotUnderSourceControlWarning": true,
      "suppressShowKeyBindingsNotice": true,
      "suppressWelcomeNotice": true
    },
    "gitlens.advanced.repositorySearchDepth": 2,
    "gitlens.autolinks": [],
    "gitlens.blame.heatmap.enabled": true,
    "gitlens.codeLens.scopes": ["document", "containers"],
    "gitlens.defaultDateFormat": "MMM DD, YYYY",
    "gitlens.gitCommands.skipConfirmations": [
      "fetch:command",
      "stash-push:command",
      "switch:command",
      "push:command"
    ],
    "gitlens.remotes": ["https://github.com/Andrews-McMeel-Universal"],
    "gitlens.sortBranchesBy": "date:desc",
    "gitlens.views.compare.enabled": true,
    "gitlens.views.search.enabled": false,
    "html.format.enable": true,
    "jira-plugin.baseUrl": "https://amuniversal.atlassian.net",
    "jira-plugin.enableCheckForNotifications": true,
    "jira-plugin.gitIntegration": true,
    "jira-plugin.groupTaskAndSubtasks": true,
    "jira-plugin.issueListAutoRefreshInterval": 5,
    "jira-plugin.projectKeyMapping": [
      "puzzlesociety=PUZSOC",
      "gocomics=GOC",
      "dilbert=DILBERT",
      "doonesbury=DOONES",
      "dailycartoonist=WP",
      "thefarside=FARSIDE",
      "uexpress=UEXPRESS",
      "universaluclick=SYND",
      "wpengine-dilbertblog=DILBERT",
      "consumer_admin=CSADMIN",
      "content_admin=CONADMIN",
      "otterloop=OTTER",
      "amu_games=GAME",
      "embedded_entertainment=GOCSERV",
      "embed_service=EMBEDSERV",
      "filemover=FILEMOVER",
      "filemover3=FILEMOVER",
      "gocomics-store-service=GOC",
      "webservice_avatars=DT",
      "webservice_content=CONSERV",
      "webservice_feature_avatars=DT",
      "webservice_gamedata=EMBEDSERV",
      "webservice_registration=CSADMIN",
      "amureprints=REPRINT",
      "uucontentsystem=CONSERV",
      "uclick-textparser-gem=CONSERV",
      "uclick-content-gem=CONSERV",
      "uclick-consumer-gem=CSADMIN",
      "uclick-registration-gem=CSADMIN",
      "uclick-contentsherpa-gem=SHERPA",
      "uclick-admin-assets-gem=CONADMIN",
      "team-tools-and-settings=DT",
      "mobile-friendly-comic-viewer=SANDBOX"
    ],
    "jira-plugin.username": "abarrows@amuniversal.com",
    "jira-plugin.workingIssueAssignees": "currentUser()",
    "jira-plugin.workingIssueStatues": "backlog, In progress, In Peer Review, In QA Review, Approved",
    "less.validate": false,
    "liveServer.settings.ChromeDebuggingAttachment": false,
    "liveServer.settings.donotShowInfoMsg": true,
    "liveServer.settings.wait": 500,
    "markdown.preview.fontSize": 16,
    "merge-conflict.autoNavigateNextConflict.enabled": true,
    "npm.packageManager": "yarn",
    "prettier.packageManager": "yarn",
    "problems.decorations.enabled": true,
    "rewrap.autoWrap.enabled": true,
    "rewrap.doubleSentenceSpacing": true,
    "scm.diffDecorations": "gutter",
    "scm.diffDecorationsGutterVisibility": "always",
    "scss.validate": false,
    "search.exclude": {
      "**/.history/**": true
    },
    "search.globalFindClipboard": true,
    "search.quickOpen.includeHistory": false,
    "search.useIgnoreFiles": false,
    "sortLines.filterBlankLines": true,
    "sortLines.sortEntireFile": true,
    "stylelint.enable": true,
    "stylelint.packageManager": "yarn",
    "terminal.external.osxExec": "iterm.app",
    "terminal.integrated.confirmOnExit": false,
    "terminal.integrated.cursorBlinking": true,
    "terminal.integrated.cursorStyle": "line",
    "terminal.integrated.enableBell": true,
    "terminal.integrated.fontSize": 16,
    "terminal.integrated.rendererType": "dom",
    "terminal.integrated.rightClickBehavior": "default",
    "todo-tree.tree.showScanModeButton": false,
    "vsicons.dontShowNewVersionMessage": true,
    "vsintellicode.modify.editor.suggestSelection": "automaticallyOverrodeDefaultValue",
    "window.newWindowDimensions": "maximized",
    "window.restoreWindows": "all",
    "window.zoomLevel": 0,
    "workbench.colorTheme": "One Dark Pro",
    "workbench.editor.highlightModifiedTabs": true,
    "workbench.editor.revealIfOpen": true,
    "workbench.editor.showTabs": true,
    "workbench.iconTheme": "material-icon-theme",
    "workbench.settings.enableNaturalLanguageSearch": false,
    "workbench.settings.openDefaultKeybindings": true,
    "workbench.settings.useSplitJSON": true,
    "workbench.tree.indent": 4,
    "workbench.view.alwaysShowHeaderActions": true
  }
}
